ev3/__init__.py
ev3/ev3.py
ev3_python-0.0.2.dist-info/LICENSE.MD
ev3_python-0.0.2.dist-info/METADATA
ev3_python-0.0.2.dist-info/WHEEL
ev3_python-0.0.2.dist-info/top_level.txt
ev3_python-0.0.2.dist-info/RECORD
