Metadata-Version: 2.1
Name: ev3-python
Version: 0.0.2
Summary: Simple library to control 'Lego™ EV3' controller
Home-page: https://github.com/vladdoth/pyEV3
Author: Vladislav Bolkunov
Author-email: vladbolkunovv@gmail.com
License: UNKNOWN
Platform: UNKNOWN
Classifier: Programming Language :: Python :: 3
Classifier: License :: OSI Approved :: MIT License
Classifier: Operating System :: OS Independent
Requires-Python: >=3.0
License-File: LICENSE.MD
Requires-Dist: pyserial
